crossnumber/__init__.py
crossnumber/cn.py
crossnumber-0.7.1.dist-info/LICENSE
crossnumber-0.7.1.dist-info/METADATA
crossnumber-0.7.1.dist-info/WHEEL
crossnumber-0.7.1.dist-info/top_level.txt
crossnumber-0.7.1.dist-info/RECORD
