Metadata-Version: 2.1
Name: crossnumber
Version: 0.7.1
Summary: A collection of Python functions which may be of use when solving crossnumber puzzles.
Home-page: https://github.com/vellender/crossnumber
Author: Adam Vellender
Author-email: dev@vellender.com
Keywords: crossnumber,solver,solve,tools,tool,puzzle,listener,magpie,numerical,numericals,crossword,mathematical,mathematicals
License-File: LICENSE
Requires-Dist: numpy
Requires-Dist: termcolor
Requires-Dist: sympy
